{"frames": {

"book":
{
	"frame": {"x":1,"y":1,"w":120,"h":120},
	"rotated": false,
	"trimmed": false,
	"spriteSourceSize": {"x":0,"y":0,"w":120,"h":120},
	"sourceSize": {"w":120,"h":120}
},
"book_shadow":
{
	"frame": {"x":122,"y":1,"w":120,"h":120},
	"rotated": false,
	"trimmed": false,
	"spriteSourceSize": {"x":0,"y":0,"w":120,"h":120},
	"sourceSize": {"w":120,"h":120}
},
"broom":
{
	"frame": {"x":1,"y":122,"w":120,"h":120},
	"rotated": false,
	"trimmed": false,
	"spriteSourceSize": {"x":0,"y":0,"w":120,"h":120},
	"sourceSize": {"w":120,"h":120}
},
"broom_shadow":
{
	"frame": {"x":122,"y":122,"w":120,"h":120},
	"rotated": false,
	"trimmed": false,
	"spriteSourceSize": {"x":0,"y":0,"w":120,"h":120},
	"sourceSize": {"w":120,"h":120}
},
"hat":
{
	"frame": {"x":1,"y":243,"w":120,"h":120},
	"rotated": false,
	"trimmed": false,
	"spriteSourceSize": {"x":0,"y":0,"w":120,"h":120},
	"sourceSize": {"w":120,"h":120}
},
"hat_shadow":
{
	"frame": {"x":122,"y":243,"w":120,"h":120},
	"rotated": false,
	"trimmed": false,
	"spriteSourceSize": {"x":0,"y":0,"w":120,"h":120},
	"sourceSize": {"w":120,"h":120}
},
"potion":
{
	"frame": {"x":1,"y":364,"w":120,"h":120},
	"rotated": false,
	"trimmed": false,
	"spriteSourceSize": {"x":0,"y":0,"w":120,"h":120},
	"sourceSize": {"w":120,"h":120}
},
"potion_shadow":
{
	"frame": {"x":122,"y":364,"w":120,"h":120},
	"rotated": false,
	"trimmed": false,
	"spriteSourceSize": {"x":0,"y":0,"w":120,"h":120},
	"sourceSize": {"w":120,"h":120}
},
"wand":
{
	"frame": {"x":1,"y":485,"w":120,"h":120},
	"rotated": false,
	"trimmed": false,
	"spriteSourceSize": {"x":0,"y":0,"w":120,"h":120},
	"sourceSize": {"w":120,"h":120}
},
"wand_shadow":
{
	"frame": {"x":122,"y":485,"w":120,"h":120},
	"rotated": false,
	"trimmed": false,
	"spriteSourceSize": {"x":0,"y":0,"w":120,"h":120},
	"sourceSize": {"w":120,"h":120}
}},
"meta": {
	"image": "magic_items2.png",
	"format": "RGBA8888",
	"size": {"w":243,"h":606},
	"scale": "1"
}
}
